dotenv_schema/__init__.py
dotenv_schema/loader.py
dotenv_schema-0.1.1.dist-info/licenses/LICENSE
dotenv_schema-0.1.1.dist-info/METADATA
dotenv_schema-0.1.1.dist-info/WHEEL
dotenv_schema-0.1.1.dist-info/top_level.txt
dotenv_schema-0.1.1.dist-info/RECORD
