Metadata-Version: 2.4
Name: dotenv-schema
Version: 0.1.1
Summary: A simple Python package to load, validate, and type-cast environment variables from .env files using a schema.
Author-email: maulome Pelumi <maulomepelumi@gmail.com>
License-Expression: MIT
Project-URL: Homepage, https://github.com/skyspec28/dotenv-schema
Project-URL: Documentation, https://github.com/skyspec28/dotenv-schema#readme
Project-URL: Bug Tracker, https://github.com/skyspec28/dotenv-schema/issues
Project-URL: Source Code, https://github.com/skyspec28/dotenv-schema
Classifier: Development Status :: 4 - Beta
Classifier: Intended Audience :: Developers
Classifier: Programming Language :: Python :: 3
Classifier: Programming Language :: Python :: 3.8
Classifier: Programming Language :: Python :: 3.9
Classifier: Programming Language :: Python :: 3.10
Classifier: Programming Language :: Python :: 3.11
Classifier: Programming Language :: Python :: 3.12
Classifier: Topic :: Software Development :: Libraries :: Python Modules
Classifier: Topic :: Utilities
Requires-Python: >=3.8
License-File: LICENSE
Provides-Extra: dev
Requires-Dist: pytest>=7.0.0; extra == "dev"
Requires-Dist: pytest-cov>=4.0.0; extra == "dev"
Dynamic: license-file
